pickled_pipeline-0.3.4.dist-info/METADATA
pickled_pipeline-0.3.4.dist-info/WHEEL
pickled_pipeline-0.3.4.dist-info/entry_points.txt
pickled_pipeline-0.3.4.dist-info/licenses/LICENSE
pickled_pipeline/__init__.py
pickled_pipeline/cache.py
pickled_pipeline/cli.py
pickled_pipeline/py.typed
pickled_pipeline-0.3.4.dist-info/RECORD
