Metadata-Version: 2.1
Name: pickled_pipeline
Version: 0.3.4
Summary: A package for caching repeat runs of pipelines that have expensive operations along the way
Author-Email: "B.T. Franklin" <brandon.franklin@gmail.com>
License: MIT License
Classifier: Programming Language :: Python :: 3
Classifier: Programming Language :: Python :: 3 :: Only
Classifier: Programming Language :: Python :: 3.10
Classifier: Programming Language :: Python :: 3.11
Classifier: Programming Language :: Python :: 3.12
Classifier: Programming Language :: Python :: 3.13
Classifier: Programming Language :: Python :: 3.14
Classifier: Typing :: Typed
Classifier: License :: OSI Approved :: MIT License
Classifier: Operating System :: OS Independent
Classifier: Intended Audience :: Developers
Classifier: Topic :: Software Development :: Libraries :: Python Modules
Project-URL: Homepage, https://github.com/btfranklin/pickled_pipeline
Project-URL: Issues, https://github.com/btfranklin/pickled_pipeline/issues
Project-URL: Changelog, https://github.com/btfranklin/pickled_pipeline/releases
Project-URL: Repository, https://github.com/btfranklin/pickled_pipeline.git
Requires-Python: >=3.10
Requires-Dist: click>=8.3.1
